{
    "code": "0",
    "message": "ok",
    "result": {
        "begin_time": "2015-09-16 16:23:35",
        "count": "37",
        "end_time": "2016-12-31 16:23:35",
        "IsActive": "1",
        "LinkPicture": "http://image13.wine9.com/activity/2016/04/other/new_01.jpg",
        "Picture": "http://images.wine9.com/activity/2015/index/index825/pj.jpg",
        "PromId": "2438",
        "PromName": "【H5/app】头部导航啤酒",
        "PromCode": "1a0ee6a02d0e4def",
        "Memo": "",
        "list": [
            {
                "LinkPicture": "http://image13.wine9.com/activity/2016/04/other/new_01.jpg",
                "Picture": "http://images.wine9.com/activity/2015/index/index825/pj.jpg",
                "Is_HaiTao": "0",
                "TotalQty": "",
                "UsableQty": "0",
                "IsSorting": "",
                "Memo": "",
                "PromId": "2438",
                "PromCode": "1a0ee6a02d0e4def",
                "PromName": "【H5/app】头部导航啤酒",
                "BeginTime": "2015-09-16 16:23:35",
                "EndTime": "2016-12-31 16:23:35",
                "IsActive": "1",
                "Sku": "21242",
                "Promote_price": "168.00",
                "goods_remark": "",
                "Area": "",
                "Is_group_goods": "1",
                "goods_id": "21242",
                "goods_img": "goods_images/21242/21242_list_20160719104703.jpg",
                "Size120_180": "goods_images/21242/21242_120_180_20160719104703.jpg",
                "img256_384": "goods_images/21242/21242_256_384_20160719104703.jpg",
                "move_img": "mobiles/mobile_goods_gallery/21242/21242_270_270_20160719104703.jpg",
                "Market_price": "0.00",
                "Shop_price": "258.00",
                "goods_name": "星堡小麦啤酒500ml【24听装】",
                "Is_book": "0",
                "Sellered": "562",
                "OriginId": "10016",
                "Cat_name": "德国",
                "SellingPoint": "心动体验，不负所见",
                "SupplyMode": "",
                "MobileHighPicture": "",
                "MobileWidePicture": "",
                "PreEndTime": "0",
                "Prepaid": "0.00",
                "PreStartTime": "0",
                "OriginCountry": "",
                "AttrSweet": "",
                "AttrTaste": "",
                "AttrScore": "",
                "AttrDegree": "",
                "ProComment": "",
                "AttrBreed": "",
                "gradescore": "95",
                "SaleQty": "4",
                "StockQty": "29",
                "yxNum": "29"
            },
            {
                "LinkPicture": "http://image13.wine9.com/activity/2016/04/other/new_01.jpg",
                "Picture": "http://images.wine9.com/activity/2015/index/index825/pj.jpg",
                "Is_HaiTao": "0",
                "TotalQty": "",
                "UsableQty": "0",
                "IsSorting": "",
                "Memo": "",
                "PromId": "2438",
                "PromCode": "1a0ee6a02d0e4def",
                "PromName": "【H5/app】头部导航啤酒",
                "BeginTime": "2015-09-16 16:23:35",
                "EndTime": "2016-12-31 16:23:35",
                "IsActive": "1",
                "Sku": "16281",
                "Promote_price": "99.00",
                "goods_remark": "",
                "Area": "",
                "Is_group_goods": "1",
                "goods_id": "16281",
                "goods_img": "goods_images/16281/16281_list_20160229050012.jpg",
                "Size120_180": "goods_images/16281/16281_120_180_20160229050012.jpg",
                "img256_384": "goods_images/16281/16281_256_384_20160229050012.jpg",
                "move_img": "mobiles/mobile_goods_gallery/16281/16281_270_270_20160229050012.jpg",
                "Market_price": "432.00",
                "Shop_price": "432.00",
                "goods_name": "【整箱】乐森堡小麦啤酒500ml*24听",
                "Is_book": "0",
                "Sellered": "23423",
                "OriginId": "10016",
                "Cat_name": "德国",
                "SellingPoint": "入口顺滑，清凉一夏",
                "SupplyMode": "",
                "MobileHighPicture": "mobiles/mobile_goods_gallery/16281/16281_MH.jpg",
                "MobileWidePicture": "mobiles/mobile_goods_gallery/16281/16281_MW.jpg",
                "PreEndTime": "0",
                "Prepaid": "0.00",
                "PreStartTime": "0",
                "OriginCountry": "",
                "AttrSweet": "",
                "AttrTaste": "",
                "AttrScore": "",
                "AttrDegree": "",
                "ProComment": "",
                "AttrBreed": "",
                "gradescore": "95",
                "SaleQty": "274",
                "StockQty": "3328",
                "yxNum": "3328"
            },
            {
                "LinkPicture": "http://image13.wine9.com/activity/2016/04/other/new_01.jpg",
                "Picture": "http://images.wine9.com/activity/2015/index/index825/pj.jpg",
                "Is_HaiTao": "0",
                "TotalQty": "",
                "UsableQty": "0",
                "IsSorting": "",
                "Memo": "",
                "PromId": "2438",
                "PromCode": "1a0ee6a02d0e4def",
                "PromName": "【H5/app】头部导航啤酒",
                "BeginTime": "2015-09-16 16:23:35",
                "EndTime": "2016-12-31 16:23:35",
                "IsActive": "1",
                "Sku": "21304",
                "Promote_price": "59.00",
                "goods_remark": "",
                "Area": "",
                "Is_group_goods": "1",
                "goods_id": "21304",
                "goods_img": "goods_images/21304/21304_list_20160728023549.jpg",
                "Size120_180": "goods_images/21304/21304_120_180_20160728023549.jpg",
                "img256_384": "goods_images/21304/21304_256_384_20160728023549.jpg",
                "move_img": "mobiles/mobile_goods_gallery/21304/21304_270_270_20160728023549.jpg",
                "Market_price": "0.00",
                "Shop_price": "79.00",
                "goods_name": "星堡黑啤酒500ml【8听装】",
                "Is_book": "0",
                "Sellered": "446",
                "OriginId": "10016",
                "Cat_name": "德国",
                "SellingPoint": "心动体验，不负所见",
                "SupplyMode": "",
                "MobileHighPicture": "",
                "MobileWidePicture": "",
                "PreEndTime": "0",
                "Prepaid": "0.00",
                "PreStartTime": "0",
                "OriginCountry": "",
                "AttrSweet": "",
                "AttrTaste": "",
                "AttrScore": "",
                "AttrDegree": "",
                "ProComment": "",
                "AttrBreed": "",
                "gradescore": "95",
                "SaleQty": "3",
                "StockQty": "120",
                "yxNum": "120"
            },
            {
                "LinkPicture": "http://image13.wine9.com/activity/2016/04/other/new_01.jpg",
                "Picture": "http://images.wine9.com/activity/2015/index/index825/pj.jpg",
                "Is_HaiTao": "0",
                "TotalQty": "",
                "UsableQty": "0",
                "IsSorting": "",
                "Memo": "",
                "PromId": "2438",
                "PromCode": "1a0ee6a02d0e4def",
                "PromName": "【H5/app】头部导航啤酒",
                "BeginTime": "2015-09-16 16:23:35",
                "EndTime": "2016-12-31 16:23:35",
                "IsActive": "1",
                "Sku": "13107",
                "Promote_price": "178.00",
                "goods_remark": "",
                "Area": "",
                "Is_group_goods": "1",
                "goods_id": "13107",
                "goods_img": "goods_images/13107/13107_list_20160414101919.jpg",
                "Size120_180": "goods_images/13107/13107_120_180_20160414101919.jpg",
                "img256_384": "goods_images/13107/13107_256_384_20160414101919.jpg",
                "move_img": "mobiles/mobile_goods_gallery/13107/13107_270_270_20160414101919.jpg",
                "Market_price": "799.00",
                "Shop_price": "799.00",
                "goods_name": "凯撒黑啤酒 500ml*24",
                "Is_book": "0",
                "Sellered": "1631",
                "OriginId": "10016",
                "Cat_name": "德国",
                "SellingPoint": "德国纯正啤酒，百年历史",
                "SupplyMode": "",
                "MobileHighPicture": "mobiles/mobile_goods_gallery/13107/13107_MH.jpg",
                "MobileWidePicture": "mobiles/mobile_goods_gallery/13107/13107_MW.jpg",
                "PreEndTime": "0",
                "Prepaid": "0.00",
                "PreStartTime": "0",
                "OriginCountry": "",
                "AttrSweet": "",
                "AttrTaste": "",
                "AttrScore": "",
                "AttrDegree": "",
                "ProComment": "",
                "AttrBreed": "",
                "gradescore": "95",
                "SaleQty": "16",
                "StockQty": "22",
                "yxNum": "22"
            },
            {
                "LinkPicture": "http://image13.wine9.com/activity/2016/04/other/new_01.jpg",
                "Picture": "http://images.wine9.com/activity/2015/index/index825/pj.jpg",
                "Is_HaiTao": "0",
                "TotalQty": "",
                "UsableQty": "0",
                "IsSorting": "",
                "Memo": "",
                "PromId": "2438",
                "PromCode": "1a0ee6a02d0e4def",
                "PromName": "【H5/app】头部导航啤酒",
                "BeginTime": "2015-09-16 16:23:35",
                "EndTime": "2016-12-31 16:23:35",
                "IsActive": "1",
                "Sku": "21305",
                "Promote_price": "59.00",
                "goods_remark": "",
                "Area": "",
                "Is_group_goods": "1",
                "goods_id": "21305",
                "goods_img": "goods_images/21305/21305_list_20160721043044.jpg",
                "Size120_180": "goods_images/21305/21305_120_180_20160721043044.jpg",
                "img256_384": "goods_images/21305/21305_256_384_20160721043044.jpg",
                "move_img": "mobiles/mobile_goods_gallery/21305/21305_270_270_20160721043044.jpg",
                "Market_price": "0.00",
                "Shop_price": "79.00",
                "goods_name": "星堡小麦啤酒500ml【8听装】",
                "Is_book": "0",
                "Sellered": "562",
                "OriginId": "10016",
                "Cat_name": "德国",
                "SellingPoint": "心动体验，不负所见",
                "SupplyMode": "",
                "MobileHighPicture": "",
                "MobileWidePicture": "",
                "PreEndTime": "0",
                "Prepaid": "0.00",
                "PreStartTime": "0",
                "OriginCountry": "",
                "AttrSweet": "",
                "AttrTaste": "",
                "AttrScore": "",
                "AttrDegree": "",
                "ProComment": "",
                "AttrBreed": "",
                "gradescore": "95",
                "SaleQty": "7",
                "StockQty": "88",
                "yxNum": "88"
            },
            {
                "LinkPicture": "http://image13.wine9.com/activity/2016/04/other/new_01.jpg",
                "Picture": "http://images.wine9.com/activity/2015/index/index825/pj.jpg",
                "Is_HaiTao": "0",
                "TotalQty": "",
                "UsableQty": "0",
                "IsSorting": "",
                "Memo": "",
                "PromId": "2438",
                "PromCode": "1a0ee6a02d0e4def",
                "PromName": "【H5/app】头部导航啤酒",
                "BeginTime": "2015-09-16 16:23:35",
                "EndTime": "2016-12-31 16:23:35",
                "IsActive": "1",
                "Sku": "20481",
                "Promote_price": "199.00",
                "goods_remark": "",
                "Area": "",
                "Is_group_goods": "1",
                "goods_id": "20481",
                "goods_img": "goods_images/20481/20481_list_20160418111858.jpg",
                "Size120_180": "goods_images/20481/20481_120_180_20160418111858.jpg",
                "img256_384": "goods_images/20481/20481_256_384_20160418111858.jpg",
                "move_img": "mobiles/mobile_goods_gallery/20481/20481_270_270_20160418111858.jpg",
                "Market_price": "0.00",
                "Shop_price": "432.00",
                "goods_name": "福佳白啤酒（Hoegaarden） 330ml【整箱】",
                "Is_book": "0",
                "Sellered": "1546",
                "OriginId": "75",
                "Cat_name": "啤酒",
                "SellingPoint": "比利时白啤酒的经典代表",
                "SupplyMode": "",
                "MobileHighPicture": "mobiles/mobile_goods_gallery/20481/20481_MH.jpg",
                "MobileWidePicture": "mobiles/mobile_goods_gallery/20481/20481_MW.jpg",
                "PreEndTime": "0",
                "Prepaid": "0.00",
                "PreStartTime": "0",
                "OriginCountry": "",
                "AttrSweet": "",
                "AttrTaste": "",
                "AttrScore": "",
                "AttrDegree": "",
                "ProComment": "",
                "AttrBreed": "",
                "gradescore": "95",
                "SaleQty": "30",
                "StockQty": "62",
                "yxNum": "62"
            },
            {
                "LinkPicture": "http://image13.wine9.com/activity/2016/04/other/new_01.jpg",
                "Picture": "http://images.wine9.com/activity/2015/index/index825/pj.jpg",
                "Is_HaiTao": "0",
                "TotalQty": "",
                "UsableQty": "0",
                "IsSorting": "",
                "Memo": "",
                "PromId": "2438",
                "PromCode": "1a0ee6a02d0e4def",
                "PromName": "【H5/app】头部导航啤酒",
                "BeginTime": "2015-09-16 16:23:35",
                "EndTime": "2016-12-31 16:23:35",
                "IsActive": "1",
                "Sku": "20934",
                "Promote_price": "99.00",
                "goods_remark": "",
                "Area": "",
                "Is_group_goods": "1",
                "goods_id": "20934",
                "goods_img": "goods_images/20934/20934_list_20160527060236.jpg",
                "Size120_180": "goods_images/20934/20934_120_180_20160527060236.jpg",
                "img256_384": "goods_images/20934/20934_256_384_20160527060236.jpg",
                "move_img": "mobiles/mobile_goods_gallery/20934/20934_270_270_20160527060236.jpg",
                "Market_price": "0.00",
                "Shop_price": "99.00",
                "goods_name": "奥堡小麦啤酒500ml+奥堡黑啤酒500ml【16听+8听】",
                "Is_book": "0",
                "Sellered": "565",
                "OriginId": "10016",
                "Cat_name": "德国",
                "SellingPoint": "生态啤酒【保质期至2016-10-25】",
                "SupplyMode": "",
                "MobileHighPicture": "",
                "MobileWidePicture": "",
                "PreEndTime": "0",
                "Prepaid": "0.00",
                "PreStartTime": "0",
                "OriginCountry": "",
                "AttrSweet": "",
                "AttrTaste": "",
                "AttrScore": "",
                "AttrDegree": "",
                "ProComment": "",
                "AttrBreed": "",
                "gradescore": "95",
                "SaleQty": "20",
                "StockQty": "23",
                "yxNum": "23"
            },
            {
                "LinkPicture": "http://image13.wine9.com/activity/2016/04/other/new_01.jpg",
                "Picture": "http://images.wine9.com/activity/2015/index/index825/pj.jpg",
                "Is_HaiTao": "0",
                "TotalQty": "",
                "UsableQty": "0",
                "IsSorting": "",
                "Memo": "",
                "PromId": "2438",
                "PromCode": "1a0ee6a02d0e4def",
                "PromName": "【H5/app】头部导航啤酒",
                "BeginTime": "2015-09-16 16:23:35",
                "EndTime": "2016-12-31 16:23:35",
                "IsActive": "1",
                "Sku": "21243",
                "Promote_price": "168.00",
                "goods_remark": "",
                "Area": "",
                "Is_group_goods": "1",
                "goods_id": "21243",
                "goods_img": "goods_images/21243/21243_list_20160719111719.jpg",
                "Size120_180": "goods_images/21243/21243_120_180_20160719111719.jpg",
                "img256_384": "goods_images/21243/21243_256_384_20160719111719.jpg",
                "move_img": "mobiles/mobile_goods_gallery/21243/21243_270_270_20160719111719.jpg",
                "Market_price": "0.00",
                "Shop_price": "258.00",
                "goods_name": "星堡黑啤酒500ml【24听装】",
                "Is_book": "0",
                "Sellered": "446",
                "OriginId": "10016",
                "Cat_name": "德国",
                "SellingPoint": "心动体验，不负所见",
                "SupplyMode": "",
                "MobileHighPicture": "",
                "MobileWidePicture": "",
                "PreEndTime": "0",
                "Prepaid": "0.00",
                "PreStartTime": "0",
                "OriginCountry": "",
                "AttrSweet": "",
                "AttrTaste": "",
                "AttrScore": "",
                "AttrDegree": "",
                "ProComment": "",
                "AttrBreed": "",
                "gradescore": "95",
                "SaleQty": "1",
                "StockQty": "40",
                "yxNum": "40"
            },
            {
                "LinkPicture": "http://image13.wine9.com/activity/2016/04/other/new_01.jpg",
                "Picture": "http://images.wine9.com/activity/2015/index/index825/pj.jpg",
                "Is_HaiTao": "0",
                "TotalQty": "",
                "UsableQty": "0",
                "IsSorting": "",
                "Memo": "",
                "PromId": "2438",
                "PromCode": "1a0ee6a02d0e4def",
                "PromName": "【H5/app】头部导航啤酒",
                "BeginTime": "2015-09-16 16:23:35",
                "EndTime": "2016-12-31 16:23:35",
                "IsActive": "1",
                "Sku": "21586",
                "Promote_price": "109.00",
                "goods_remark": "",
                "Area": "",
                "Is_group_goods": "1",
                "goods_id": "21586",
                "goods_img": "goods_images/21586/21586_list_20160812110613.jpg",
                "Size120_180": "goods_images/21586/21586_120_180_20160812110613.jpg",
                "img256_384": "goods_images/21586/21586_256_384_20160812110613.jpg",
                "move_img": "mobiles/mobile_goods_gallery/21586/21586_270_270_20160812110613.jpg",
                "Market_price": "0.00",
                "Shop_price": "199.00",
                "goods_name": "勇士黑啤酒500ml 【整箱】",
                "Is_book": "0",
                "Sellered": "0",
                "OriginId": "10016",
                "Cat_name": "德国",
                "SellingPoint": "德国原装进口，始终恪守遵循德国质量纯度法案\r\n（2017到期）",
                "SupplyMode": "",
                "MobileHighPicture": "",
                "MobileWidePicture": "",
                "PreEndTime": "0",
                "Prepaid": "0.00",
                "PreStartTime": "0",
                "OriginCountry": "",
                "AttrSweet": "",
                "AttrTaste": "",
                "AttrScore": "",
                "AttrDegree": "",
                "ProComment": "",
                "AttrBreed": "",
                "gradescore": "95",
                "SaleQty": "",
                "StockQty": "710",
                "yxNum": "710"
            },
            {
                "LinkPicture": "http://image13.wine9.com/activity/2016/04/other/new_01.jpg",
                "Picture": "http://images.wine9.com/activity/2015/index/index825/pj.jpg",
                "Is_HaiTao": "0",
                "TotalQty": "",
                "UsableQty": "0",
                "IsSorting": "",
                "Memo": "",
                "PromId": "2438",
                "PromCode": "1a0ee6a02d0e4def",
                "PromName": "【H5/app】头部导航啤酒",
                "BeginTime": "2015-09-16 16:23:35",
                "EndTime": "2016-12-31 16:23:35",
                "IsActive": "1",
                "Sku": "15931",
                "Promote_price": "129.00",
                "goods_remark": "",
                "Area": "",
                "Is_group_goods": "1",
                "goods_id": "15931",
                "goods_img": "goods_images/15931/15931_list_20160227060524.jpg",
                "Size120_180": "goods_images/15931/15931_120_180_20160227060524.jpg",
                "img256_384": "goods_images/15931/15931_256_384_20160227060524.jpg",
                "move_img": "mobiles/mobile_goods_gallery/15931/15931_270_270_20160227060524.jpg",
                "Market_price": "0.00",
                "Shop_price": "432.00",
                "goods_name": "索伦堡黑啤酒 500ML【24听】",
                "Is_book": "0",
                "Sellered": "691",
                "OriginId": "10016",
                "Cat_name": "德国",
                "SellingPoint": "德国原装进口，始终恪守遵循德国质量纯度法案\r\n",
                "SupplyMode": "",
                "MobileHighPicture": "mobiles/mobile_goods_gallery/15931/15931_MH.jpg",
                "MobileWidePicture": "mobiles/mobile_goods_gallery/15931/15931_MW.jpg",
                "PreEndTime": "0",
                "Prepaid": "0.00",
                "PreStartTime": "0",
                "OriginCountry": "",
                "AttrSweet": "",
                "AttrTaste": "",
                "AttrScore": "",
                "AttrDegree": "",
                "ProComment": "",
                "AttrBreed": "",
                "gradescore": "95",
                "SaleQty": "25",
                "StockQty": "867",
                "yxNum": "867"
            },
            {
                "LinkPicture": "http://image13.wine9.com/activity/2016/04/other/new_01.jpg",
                "Picture": "http://images.wine9.com/activity/2015/index/index825/pj.jpg",
                "Is_HaiTao": "0",
                "TotalQty": "",
                "UsableQty": "0",
                "IsSorting": "",
                "Memo": "",
                "PromId": "2438",
                "PromCode": "1a0ee6a02d0e4def",
                "PromName": "【H5/app】头部导航啤酒",
                "BeginTime": "2015-09-16 16:23:35",
                "EndTime": "2016-12-31 16:23:35",
                "IsActive": "1",
                "Sku": "13359",
                "Promote_price": "99.00",
                "goods_remark": "",
                "Area": "",
                "Is_group_goods": "1",
                "goods_id": "13359",
                "goods_img": "goods_images/13359/13359_list_20160229113522.jpg",
                "Size120_180": "goods_images/13359/13359_120_180_20160229113522.jpg",
                "img256_384": "goods_images/13359/13359_256_384_20160229113522.jpg",
                "move_img": "mobiles/mobile_goods_gallery/13359/13359_270_270_20160229113522.jpg",
                "Market_price": "0.00",
                "Shop_price": "360.00",
                "goods_name": "斯汀伯格黑啤酒*24听",
                "Is_book": "0",
                "Sellered": "3074",
                "OriginId": "10016",
                "Cat_name": "德国",
                "SellingPoint": "德国知名啤酒品牌，啤酒中的液体面包",
                "SupplyMode": "",
                "MobileHighPicture": "mobiles/mobile_goods_gallery/13359/13359_MH.jpg",
                "MobileWidePicture": "mobiles/mobile_goods_gallery/13359/13359_MW.jpg",
                "PreEndTime": "-201600",
                "Prepaid": "0.00",
                "PreStartTime": "-201600",
                "OriginCountry": "",
                "AttrSweet": "",
                "AttrTaste": "",
                "AttrScore": "",
                "AttrDegree": "",
                "ProComment": "",
                "AttrBreed": "",
                "gradescore": "95",
                "SaleQty": "128",
                "StockQty": "419",
                "yxNum": "419"
            },
            {
                "LinkPicture": "http://image13.wine9.com/activity/2016/04/other/new_01.jpg",
                "Picture": "http://images.wine9.com/activity/2015/index/index825/pj.jpg",
                "Is_HaiTao": "0",
                "TotalQty": "",
                "UsableQty": "0",
                "IsSorting": "",
                "Memo": "",
                "PromId": "2438",
                "PromCode": "1a0ee6a02d0e4def",
                "PromName": "【H5/app】头部导航啤酒",
                "BeginTime": "2015-09-16 16:23:35",
                "EndTime": "2016-12-31 16:23:35",
                "IsActive": "1",
                "Sku": "16283",
                "Promote_price": "99.00",
                "goods_remark": "",
                "Area": "",
                "Is_group_goods": "1",
                "goods_id": "16283",
                "goods_img": "goods_images/16283/16283_list_20160227025614.jpg",
                "Size120_180": "goods_images/16283/16283_120_180_20160227025614.jpg",
                "img256_384": "goods_images/16283/16283_256_384_20160227025614.jpg",
                "move_img": "mobiles/mobile_goods_gallery/16283/16283_270_270_20160227025614.jpg",
                "Market_price": "432.00",
                "Shop_price": "432.00",
                "goods_name": "【整箱】沃多福小麦啤酒500ml*24听",
                "Is_book": "0",
                "Sellered": "23533",
                "OriginId": "10016",
                "Cat_name": "德国",
                "SellingPoint": "德国精致酿造",
                "SupplyMode": "",
                "MobileHighPicture": "mobiles/mobile_goods_gallery/16283/16283_MH.jpg",
                "MobileWidePicture": "mobiles/mobile_goods_gallery/16283/16283_MW.jpg",
                "PreEndTime": "0",
                "Prepaid": "0.00",
                "PreStartTime": "0",
                "OriginCountry": "",
                "AttrSweet": "",
                "AttrTaste": "",
                "AttrScore": "",
                "AttrDegree": "",
                "ProComment": "",
                "AttrBreed": "",
                "gradescore": "95",
                "SaleQty": "57",
                "StockQty": "1284",
                "yxNum": "1284"
            },
            {
                "LinkPicture": "http://image13.wine9.com/activity/2016/04/other/new_01.jpg",
                "Picture": "http://images.wine9.com/activity/2015/index/index825/pj.jpg",
                "Is_HaiTao": "0",
                "TotalQty": "",
                "UsableQty": "0",
                "IsSorting": "",
                "Memo": "",
                "PromId": "2438",
                "PromCode": "1a0ee6a02d0e4def",
                "PromName": "【H5/app】头部导航啤酒",
                "BeginTime": "2015-09-16 16:23:35",
                "EndTime": "2016-12-31 16:23:35",
                "IsActive": "1",
                "Sku": "21191",
                "Promote_price": "99.00",
                "goods_remark": "",
                "Area": "",
                "Is_group_goods": "1",
                "goods_id": "21191",
                "goods_img": "goods_images/21191/21191_list_20160625031538.jpg",
                "Size120_180": "goods_images/21191/21191_120_180_20160625031538.jpg",
                "img256_384": "goods_images/21191/21191_256_384_20160625031538.jpg",
                "move_img": "mobiles/mobile_goods_gallery/21191/21191_270_270_20160625031538.jpg",
                "Market_price": "0.00",
                "Shop_price": "99.00",
                "goods_name": "猎人小麦啤500ML【整箱】",
                "Is_book": "0",
                "Sellered": "4528",
                "OriginId": "75",
                "Cat_name": "啤酒",
                "SellingPoint": "德国进口啤酒，口感纯正（保质期至2016.10.18）",
                "SupplyMode": "",
                "MobileHighPicture": "",
                "MobileWidePicture": "",
                "PreEndTime": "0",
                "Prepaid": "0.00",
                "PreStartTime": "0",
                "OriginCountry": "",
                "AttrSweet": "",
                "AttrTaste": "",
                "AttrScore": "",
                "AttrDegree": "",
                "ProComment": "",
                "AttrBreed": "",
                "gradescore": "95",
                "SaleQty": "11",
                "StockQty": "723",
                "yxNum": "723"
            },
            {
                "LinkPicture": "http://image13.wine9.com/activity/2016/04/other/new_01.jpg",
                "Picture": "http://images.wine9.com/activity/2015/index/index825/pj.jpg",
                "Is_HaiTao": "0",
                "TotalQty": "",
                "UsableQty": "0",
                "IsSorting": "0",
                "Memo": "",
                "PromId": "2438",
                "PromCode": "1a0ee6a02d0e4def",
                "PromName": "【H5/app】头部导航啤酒",
                "BeginTime": "2015-09-16 16:23:35",
                "EndTime": "2016-12-31 16:23:35",
                "IsActive": "1",
                "Sku": "12490",
                "Promote_price": "69.00",
                "goods_remark": "",
                "Area": "",
                "Is_group_goods": "0",
                "goods_id": "12490",
                "goods_img": "goods_images/12490/12490_list_20150317103942.jpg",
                "Size120_180": "goods_images/12490/12490_120_180_20150317103942.jpg",
                "img256_384": "goods_images/12490/12490_256_384_20150317103942.jpg",
                "move_img": "mobiles/mobile_goods_gallery/12490/12490_270_270_20150317103942.jpg",
                "Market_price": "288.00",
                "Shop_price": "188.00",
                "goods_name": "斯汀伯格小麦啤酒 5L",
                "Is_book": "0",
                "Sellered": "1767",
                "OriginId": "10016",
                "Cat_name": "德国",
                "SellingPoint": "来自德国的‘小星星’",
                "SupplyMode": "",
                "MobileHighPicture": "mobiles/mobile_goods_gallery/12490/12490_MH.jpg",
                "MobileWidePicture": "mobiles/mobile_goods_gallery/12490/12490_MW.jpg",
                "PreEndTime": "-28800",
                "Prepaid": "0.00",
                "PreStartTime": "-28800",
                "OriginCountry": "",
                "AttrSweet": "",
                "AttrTaste": "",
                "AttrScore": "",
                "AttrDegree": "",
                "ProComment": "",
                "AttrBreed": "",
                "gradescore": "95",
                "SaleQty": "41",
                "StockQty": "39",
                "yxNum": "39"
            },
            {
                "LinkPicture": "http://image13.wine9.com/activity/2016/04/other/new_01.jpg",
                "Picture": "http://images.wine9.com/activity/2015/index/index825/pj.jpg",
                "Is_HaiTao": "0",
                "TotalQty": "",
                "UsableQty": "0",
                "IsSorting": "0",
                "Memo": "",
                "PromId": "2438",
                "PromCode": "1a0ee6a02d0e4def",
                "PromName": "【H5/app】头部导航啤酒",
                "BeginTime": "2015-09-16 16:23:35",
                "EndTime": "2016-12-31 16:23:35",
                "IsActive": "1",
                "Sku": "15988",
                "Promote_price": "69.00",
                "goods_remark": "",
                "Area": "",
                "Is_group_goods": "0",
                "goods_id": "15988",
                "goods_img": "goods_images/15988/15988_list_20151216115503.jpg",
                "Size120_180": "goods_images/15988/15988_120_180_20151216115503.jpg",
                "img256_384": "goods_images/15988/15988_256_384_20151216115503.jpg",
                "move_img": "mobiles/mobile_goods_gallery/15988/15988_270_270_20151216115503.jpg",
                "Market_price": "288.00",
                "Shop_price": "238.00",
                "goods_name": "斯汀伯格黑啤 5L",
                "Is_book": "0",
                "Sellered": "1516",
                "OriginId": "10016",
                "Cat_name": "德国",
                "SellingPoint": "来自德国的金奖‘小星星’",
                "SupplyMode": "",
                "MobileHighPicture": "mobiles/mobile_goods_gallery/15988/15988_MH.jpg",
                "MobileWidePicture": "mobiles/mobile_goods_gallery/15988/15988_MW.jpg",
                "PreEndTime": "0",
                "Prepaid": "0.00",
                "PreStartTime": "0",
                "OriginCountry": "",
                "AttrSweet": "",
                "AttrTaste": "",
                "AttrScore": "",
                "AttrDegree": "",
                "ProComment": "",
                "AttrBreed": "",
                "gradescore": "95",
                "SaleQty": "30",
                "StockQty": "22",
                "yxNum": "22"
            },
            {
                "LinkPicture": "http://image13.wine9.com/activity/2016/04/other/new_01.jpg",
                "Picture": "http://images.wine9.com/activity/2015/index/index825/pj.jpg",
                "Is_HaiTao": "0",
                "TotalQty": "",
                "UsableQty": "0",
                "IsSorting": "",
                "Memo": "",
                "PromId": "2438",
                "PromCode": "1a0ee6a02d0e4def",
                "PromName": "【H5/app】头部导航啤酒",
                "BeginTime": "2015-09-16 16:23:35",
                "EndTime": "2016-12-31 16:23:35",
                "IsActive": "1",
                "Sku": "17087",
                "Promote_price": "89.00",
                "goods_remark": "",
                "Area": "",
                "Is_group_goods": "1",
                "goods_id": "17087",
                "goods_img": "goods_images/17087/17087_list_20160227024904.jpg",
                "Size120_180": "goods_images/17087/17087_120_180_20160227024904.jpg",
                "img256_384": "goods_images/17087/17087_256_384_20160227024904.jpg",
                "move_img": "mobiles/mobile_goods_gallery/17087/17087_270_270_20160227024904.jpg",
                "Market_price": "0.00",
                "Shop_price": "216.00",
                "goods_name": "沃多福小麦啤酒500ml*12听装整箱",
                "Is_book": "0",
                "Sellered": "24080",
                "OriginId": "10016",
                "Cat_name": "德国",
                "SellingPoint": "夏日必选",
                "SupplyMode": "",
                "MobileHighPicture": "mobiles/mobile_goods_gallery/17087/17087_MH.jpg",
                "MobileWidePicture": "mobiles/mobile_goods_gallery/17087/17087_MW.jpg",
                "PreEndTime": "0",
                "Prepaid": "10.00",
                "PreStartTime": "0",
                "OriginCountry": "",
                "AttrSweet": "发酵物 绿色水果 ",
                "AttrTaste": "酸甜如初恋",
                "AttrScore": [
                    {
                        "Attr_value": "",
                        "Score": ""
                    }
                ],
                "AttrDegree": "QBA",
                "ProComment": "圣母之乳是德国弗里茨-温迪诗酒庄出品的一款经典白葡萄酒，具有甘冽甜美的新鲜果香，入口清爽宜人，是非常适合各种场合饮用的德国葡萄酒。",
                "AttrBreed": " %西万尼 %雷司令 %科万尼",
                "gradescore": "95",
                "SaleQty": "5",
                "StockQty": "2568",
                "yxNum": "2568"
            },
            {
                "LinkPicture": "http://image13.wine9.com/activity/2016/04/other/new_01.jpg",
                "Picture": "http://images.wine9.com/activity/2015/index/index825/pj.jpg",
                "Is_HaiTao": "0",
                "TotalQty": "",
                "UsableQty": "0",
                "IsSorting": "",
                "Memo": "",
                "PromId": "2438",
                "PromCode": "1a0ee6a02d0e4def",
                "PromName": "【H5/app】头部导航啤酒",
                "BeginTime": "2015-09-16 16:23:35",
                "EndTime": "2016-12-31 16:23:35",
                "IsActive": "1",
                "Sku": "21205",
                "Promote_price": "59.00",
                "goods_remark": "",
                "Area": "",
                "Is_group_goods": "1",
                "goods_id": "21205",
                "goods_img": "goods_images/21205/21205_list_20160625034634.jpg",
                "Size120_180": "goods_images/21205/21205_120_180_20160625034634.jpg",
                "img256_384": "goods_images/21205/21205_256_384_20160625034634.jpg",
                "move_img": "mobiles/mobile_goods_gallery/21205/21205_270_270_20160625034634.jpg",
                "Market_price": "0.00",
                "Shop_price": "59.00",
                "goods_name": "斯汀伯格小麦啤酒500ML(2016)【12听装】",
                "Is_book": "0",
                "Sellered": "0",
                "OriginId": "75",
                "Cat_name": "啤酒",
                "SellingPoint": "德国知名啤酒品牌，啤酒中的液体面包(2016.9.19到期)",
                "SupplyMode": "",
                "MobileHighPicture": "",
                "MobileWidePicture": "",
                "PreEndTime": "0",
                "Prepaid": "0.00",
                "PreStartTime": "0",
                "OriginCountry": "",
                "AttrSweet": "",
                "AttrTaste": "",
                "AttrScore": [
                    {
                        "Attr_value": "",
                        "Score": ""
                    }
                ],
                "AttrDegree": "",
                "ProComment": "",
                "AttrBreed": "",
                "gradescore": "95",
                "SaleQty": "7",
                "StockQty": "21",
                "yxNum": "21"
            },
            {
                "LinkPicture": "http://image13.wine9.com/activity/2016/04/other/new_01.jpg",
                "Picture": "http://images.wine9.com/activity/2015/index/index825/pj.jpg",
                "Is_HaiTao": "0",
                "TotalQty": "",
                "UsableQty": "0",
                "IsSorting": "",
                "Memo": "",
                "PromId": "2438",
                "PromCode": "1a0ee6a02d0e4def",
                "PromName": "【H5/app】头部导航啤酒",
                "BeginTime": "2015-09-16 16:23:35",
                "EndTime": "2016-12-31 16:23:35",
                "IsActive": "1",
                "Sku": "21208",
                "Promote_price": "59.00",
                "goods_remark": "",
                "Area": "",
                "Is_group_goods": "1",
                "goods_id": "21208",
                "goods_img": "goods_images/21208/21208_list_20160625040558.jpg",
                "Size120_180": "goods_images/21208/21208_120_180_20160625040558.jpg",
                "img256_384": "goods_images/21208/21208_256_384_20160625040558.jpg",
                "move_img": "mobiles/mobile_goods_gallery/21208/21208_270_270_20160625040558.jpg",
                "Market_price": "0.00",
                "Shop_price": "59.00",
                "goods_name": "奥堡黑啤酒500ml 【12听装】",
                "Is_book": "0",
                "Sellered": "0",
                "OriginId": "75",
                "Cat_name": "啤酒",
                "SellingPoint": "泡沫丰富，口味厚重(2016.11.06到期）",
                "SupplyMode": "",
                "MobileHighPicture": "",
                "MobileWidePicture": "",
                "PreEndTime": "0",
                "Prepaid": "0.00",
                "PreStartTime": "0",
                "OriginCountry": "",
                "AttrSweet": "",
                "AttrTaste": "",
                "AttrScore": [
                    {
                        "Attr_value": "",
                        "Score": ""
                    }
                ],
                "AttrDegree": "",
                "ProComment": "",
                "AttrBreed": "",
                "gradescore": "95",
                "SaleQty": "4",
                "StockQty": "1395",
                "yxNum": "1395"
            },
            {
                "LinkPicture": "http://image13.wine9.com/activity/2016/04/other/new_01.jpg",
                "Picture": "http://images.wine9.com/activity/2015/index/index825/pj.jpg",
                "Is_HaiTao": "0",
                "TotalQty": "",
                "UsableQty": "0",
                "IsSorting": "",
                "Memo": "",
                "PromId": "2438",
                "PromCode": "1a0ee6a02d0e4def",
                "PromName": "【H5/app】头部导航啤酒",
                "BeginTime": "2015-09-16 16:23:35",
                "EndTime": "2016-12-31 16:23:35",
                "IsActive": "1",
                "Sku": "17085",
                "Promote_price": "79.00",
                "goods_remark": "",
                "Area": "",
                "Is_group_goods": "1",
                "goods_id": "17085",
                "goods_img": "goods_images/17085/17085_list_20160229023511.jpg",
                "Size120_180": "goods_images/17085/17085_120_180_20160229023511.jpg",
                "img256_384": "goods_images/17085/17085_256_384_20160229023511.jpg",
                "move_img": "mobiles/mobile_goods_gallery/17085/17085_270_270_20160229023511.jpg",
                "Market_price": "0.00",
                "Shop_price": "216.00",
                "goods_name": "乐森堡小麦啤酒500ml*12听装整箱",
                "Is_book": "0",
                "Sellered": "23919",
                "OriginId": "10016",
                "Cat_name": "德国",
                "SellingPoint": "夏日必选",
                "SupplyMode": "",
                "MobileHighPicture": "mobiles/mobile_goods_gallery/17085/17085_MH.jpg",
                "MobileWidePicture": "mobiles/mobile_goods_gallery/17085/17085_MW.jpg",
                "PreEndTime": "0",
                "Prepaid": "0.00",
                "PreStartTime": "0",
                "OriginCountry": "",
                "AttrSweet": "发酵物 绿色水果 ",
                "AttrTaste": "酸甜如初恋",
                "AttrScore": [
                    {
                        "Attr_value": "",
                        "Score": ""
                    }
                ],
                "AttrDegree": "QBA",
                "ProComment": "圣母之乳是德国弗里茨-温迪诗酒庄出品的一款经典白葡萄酒，具有甘冽甜美的新鲜果香，入口清爽宜人，是非常适合各种场合饮用的德国葡萄酒。",
                "AttrBreed": " %西万尼 %雷司令 %科万尼",
                "gradescore": "95",
                "SaleQty": "9",
                "StockQty": "6657",
                "yxNum": "6657"
            },
            {
                "LinkPicture": "http://image13.wine9.com/activity/2016/04/other/new_01.jpg",
                "Picture": "http://images.wine9.com/activity/2015/index/index825/pj.jpg",
                "Is_HaiTao": "0",
                "TotalQty": "",
                "UsableQty": "0",
                "IsSorting": "",
                "Memo": "",
                "PromId": "2438",
                "PromCode": "1a0ee6a02d0e4def",
                "PromName": "【H5/app】头部导航啤酒",
                "BeginTime": "2015-09-16 16:23:35",
                "EndTime": "2016-12-31 16:23:35",
                "IsActive": "1",
                "Sku": "13101",
                "Promote_price": "79.00",
                "goods_remark": "",
                "Area": "",
                "Is_group_goods": "1",
                "goods_id": "13101",
                "goods_img": "goods_images/13101/13101_list_20160624034439.jpg",
                "Size120_180": "goods_images/13101/13101_120_180_20160624034439.jpg",
                "img256_384": "goods_images/13101/13101_256_384_20160624034439.jpg",
                "move_img": "mobiles/mobile_goods_gallery/13101/13101_270_270_20160624034439.jpg",
                "Market_price": "0.00",
                "Shop_price": "216.00",
                "goods_name": "斯汀伯格黑啤 500ML*12听",
                "Is_book": "0",
                "Sellered": "2774",
                "OriginId": "10016",
                "Cat_name": "德国",
                "SellingPoint": "德国知名啤酒品牌，啤酒中的液体面包",
                "SupplyMode": "",
                "MobileHighPicture": "mobiles/mobile_goods_gallery/13101/13101_MH.jpg",
                "MobileWidePicture": "mobiles/mobile_goods_gallery/13101/13101_MW.jpg",
                "PreEndTime": "-201600",
                "Prepaid": "0.00",
                "PreStartTime": "-201600",
                "OriginCountry": "",
                "AttrSweet": "",
                "AttrTaste": "",
                "AttrScore": [
                    {
                        "Attr_value": "",
                        "Score": ""
                    }
                ],
                "AttrDegree": "",
                "ProComment": "",
                "AttrBreed": "",
                "gradescore": "95",
                "SaleQty": "9",
                "StockQty": "837",
                "yxNum": "837"
            },
            {
                "LinkPicture": "http://image13.wine9.com/activity/2016/04/other/new_01.jpg",
                "Picture": "http://images.wine9.com/activity/2015/index/index825/pj.jpg",
                "Is_HaiTao": "0",
                "TotalQty": "",
                "UsableQty": "0",
                "IsSorting": "",
                "Memo": "",
                "PromId": "2438",
                "PromCode": "1a0ee6a02d0e4def",
                "PromName": "【H5/app】头部导航啤酒",
                "BeginTime": "2015-09-16 16:23:35",
                "EndTime": "2016-12-31 16:23:35",
                "IsActive": "1",
                "Sku": "21203",
                "Promote_price": "59.00",
                "goods_remark": "",
                "Area": "",
                "Is_group_goods": "1",
                "goods_id": "21203",
                "goods_img": "goods_images/21203/21203_list_20160625032336.jpg",
                "Size120_180": "goods_images/21203/21203_120_180_20160625032336.jpg",
                "img256_384": "goods_images/21203/21203_256_384_20160625032336.jpg",
                "move_img": "mobiles/mobile_goods_gallery/21203/21203_270_270_20160625032336.jpg",
                "Market_price": "0.00",
                "Shop_price": "59.00",
                "goods_name": "猎人小麦啤500ML【12听装】",
                "Is_book": "0",
                "Sellered": "0",
                "OriginId": "75",
                "Cat_name": "啤酒",
                "SellingPoint": "德国进口啤酒，口感纯正（保质期至2016.10.18）",
                "SupplyMode": "",
                "MobileHighPicture": "",
                "MobileWidePicture": "",
                "PreEndTime": "0",
                "Prepaid": "0.00",
                "PreStartTime": "0",
                "OriginCountry": "",
                "AttrSweet": "",
                "AttrTaste": "",
                "AttrScore": [
                    {
                        "Attr_value": "",
                        "Score": ""
                    }
                ],
                "AttrDegree": "",
                "ProComment": "",
                "AttrBreed": "",
                "gradescore": "95",
                "SaleQty": "4",
                "StockQty": "1446",
                "yxNum": "1446"
            },
            {
                "LinkPicture": "http://image13.wine9.com/activity/2016/04/other/new_01.jpg",
                "Picture": "http://images.wine9.com/activity/2015/index/index825/pj.jpg",
                "Is_HaiTao": "0",
                "TotalQty": "",
                "UsableQty": "0",
                "IsSorting": "",
                "Memo": "",
                "PromId": "2438",
                "PromCode": "1a0ee6a02d0e4def",
                "PromName": "【H5/app】头部导航啤酒",
                "BeginTime": "2015-09-16 16:23:35",
                "EndTime": "2016-12-31 16:23:35",
                "IsActive": "1",
                "Sku": "21204",
                "Promote_price": "59.00",
                "goods_remark": "",
                "Area": "",
                "Is_group_goods": "1",
                "goods_id": "21204",
                "goods_img": "goods_images/21204/21204_list_20160625033514.jpg",
                "Size120_180": "goods_images/21204/21204_120_180_20160625033514.jpg",
                "img256_384": "goods_images/21204/21204_256_384_20160625033514.jpg",
                "move_img": "mobiles/mobile_goods_gallery/21204/21204_270_270_20160625033514.jpg",
                "Market_price": "0.00",
                "Shop_price": "59.00",
                "goods_name": "猎人黑啤500ML【12听装】",
                "Is_book": "0",
                "Sellered": "0",
                "OriginId": "75",
                "Cat_name": "啤酒",
                "SellingPoint": "口味醇厚，入口清凉口感（保质期至2016.10.1）",
                "SupplyMode": "",
                "MobileHighPicture": "",
                "MobileWidePicture": "",
                "PreEndTime": "0",
                "Prepaid": "0.00",
                "PreStartTime": "0",
                "OriginCountry": "",
                "AttrSweet": "",
                "AttrTaste": "",
                "AttrScore": [
                    {
                        "Attr_value": "",
                        "Score": ""
                    }
                ],
                "AttrDegree": "",
                "ProComment": "",
                "AttrBreed": "",
                "gradescore": "95",
                "SaleQty": "4",
                "StockQty": "443",
                "yxNum": "443"
            },
            {
                "LinkPicture": "http://image13.wine9.com/activity/2016/04/other/new_01.jpg",
                "Picture": "http://images.wine9.com/activity/2015/index/index825/pj.jpg",
                "Is_HaiTao": "0",
                "TotalQty": "0",
                "UsableQty": "0",
                "IsSorting": "",
                "Memo": "",
                "PromId": "2438",
                "PromCode": "1a0ee6a02d0e4def",
                "PromName": "【H5/app】头部导航啤酒",
                "BeginTime": "2015-09-16 16:23:35",
                "EndTime": "2016-12-31 16:23:35",
                "IsActive": "1",
                "Sku": "17526",
                "Promote_price": "89.00",
                "goods_remark": "",
                "Area": "",
                "Is_group_goods": "1",
                "goods_id": "17526",
                "goods_img": "goods_images/17526/17526_list_20160227060327.jpg",
                "Size120_180": "goods_images/17526/17526_120_180_20160227060327.jpg",
                "img256_384": "goods_images/17526/17526_256_384_20160227060327.jpg",
                "move_img": "mobiles/mobile_goods_gallery/17526/17526_270_270_20160227060327.jpg",
                "Market_price": "0.00",
                "Shop_price": "216.00",
                "goods_name": "索伦堡黑啤酒 500ML【12听装】",
                "Is_book": "0",
                "Sellered": "1029",
                "OriginId": "10016",
                "Cat_name": "德国",
                "SellingPoint": "德国原装进口，始终恪守遵循德国质量纯度法案\r\n",
                "SupplyMode": "",
                "MobileHighPicture": "mobiles/mobile_goods_gallery/17526/17526_MH.jpg",
                "MobileWidePicture": "mobiles/mobile_goods_gallery/17526/17526_MW.jpg",
                "PreEndTime": "0",
                "Prepaid": "0.00",
                "PreStartTime": "0",
                "OriginCountry": "",
                "AttrSweet": "",
                "AttrTaste": "",
                "AttrScore": [
                    {
                        "Attr_value": "",
                        "Score": ""
                    }
                ],
                "AttrDegree": "",
                "ProComment": "",
                "AttrBreed": "",
                "gradescore": "95",
                "SaleQty": "3",
                "StockQty": "1734",
                "yxNum": "1734"
            },
            {
                "LinkPicture": "http://image13.wine9.com/activity/2016/04/other/new_01.jpg",
                "Picture": "http://images.wine9.com/activity/2015/index/index825/pj.jpg",
                "Is_HaiTao": "0",
                "TotalQty": "",
                "UsableQty": "0",
                "IsSorting": "",
                "Memo": "",
                "PromId": "2438",
                "PromCode": "1a0ee6a02d0e4def",
                "PromName": "【H5/app】头部导航啤酒",
                "BeginTime": "2015-09-16 16:23:35",
                "EndTime": "2016-12-31 16:23:35",
                "IsActive": "1",
                "Sku": "21196",
                "Promote_price": "99.00",
                "goods_remark": "",
                "Area": "",
                "Is_group_goods": "1",
                "goods_id": "21196",
                "goods_img": "goods_images/21196/21196_list_20160625035943.jpg",
                "Size120_180": "goods_images/21196/21196_120_180_20160625035943.jpg",
                "img256_384": "goods_images/21196/21196_256_384_20160625035943.jpg",
                "move_img": "mobiles/mobile_goods_gallery/21196/21196_270_270_20160625035943.jpg",
                "Market_price": "0.00",
                "Shop_price": "99.00",
                "goods_name": "奥堡黑啤酒500ml 【整箱】",
                "Is_book": "0",
                "Sellered": "0",
                "OriginId": "75",
                "Cat_name": "啤酒",
                "SellingPoint": "泡沫丰富，口味厚重(2016.11.09到期)",
                "SupplyMode": "",
                "MobileHighPicture": "",
                "MobileWidePicture": "",
                "PreEndTime": "0",
                "Prepaid": "0.00",
                "PreStartTime": "0",
                "OriginCountry": "",
                "AttrSweet": "",
                "AttrTaste": "",
                "AttrScore": [
                    {
                        "Attr_value": "",
                        "Score": ""
                    }
                ],
                "AttrDegree": "",
                "ProComment": "",
                "AttrBreed": "",
                "gradescore": "95",
                "SaleQty": "12",
                "StockQty": "697",
                "yxNum": "697"
            },
            {
                "LinkPicture": "http://image13.wine9.com/activity/2016/04/other/new_01.jpg",
                "Picture": "http://images.wine9.com/activity/2015/index/index825/pj.jpg",
                "Is_HaiTao": "0",
                "TotalQty": "",
                "UsableQty": "0",
                "IsSorting": "",
                "Memo": "",
                "PromId": "2438",
                "PromCode": "1a0ee6a02d0e4def",
                "PromName": "【H5/app】头部导航啤酒",
                "BeginTime": "2015-09-16 16:23:35",
                "EndTime": "2016-12-31 16:23:35",
                "IsActive": "1",
                "Sku": "21587",
                "Promote_price": "39.00",
                "goods_remark": "",
                "Area": "",
                "Is_group_goods": "1",
                "goods_id": "21587",
                "goods_img": "goods_images/21587/21587_list_20160812111054.jpg",
                "Size120_180": "goods_images/21587/21587_120_180_20160812111054.jpg",
                "img256_384": "goods_images/21587/21587_256_384_20160812111054.jpg",
                "move_img": "mobiles/mobile_goods_gallery/21587/21587_270_270_20160812111054.jpg",
                "Market_price": "0.00",
                "Shop_price": "199.00",
                "goods_name": "勇士黑啤酒500ml 【8听装】",
                "Is_book": "0",
                "Sellered": "0",
                "OriginId": "10016",
                "Cat_name": "德国",
                "SellingPoint": "德国原装进口，始终恪守遵循德国质量纯度法案\r\n(2017到期）",
                "SupplyMode": "",
                "MobileHighPicture": "",
                "MobileWidePicture": "",
                "PreEndTime": "0",
                "Prepaid": "0.00",
                "PreStartTime": "0",
                "OriginCountry": "",
                "AttrSweet": "",
                "AttrTaste": "",
                "AttrScore": [
                    {
                        "Attr_value": "",
                        "Score": ""
                    }
                ],
                "AttrDegree": "",
                "ProComment": "",
                "AttrBreed": "",
                "gradescore": "95",
                "SaleQty": "",
                "StockQty": "17050",
                "yxNum": "17050"
            },
            {
                "LinkPicture": "http://image13.wine9.com/activity/2016/04/other/new_01.jpg",
                "Picture": "http://images.wine9.com/activity/2015/index/index825/pj.jpg",
                "Is_HaiTao": "0",
                "TotalQty": "",
                "UsableQty": "0",
                "IsSorting": "",
                "Memo": "",
                "PromId": "2438",
                "PromCode": "1a0ee6a02d0e4def",
                "PromName": "【H5/app】头部导航啤酒",
                "BeginTime": "2015-09-16 16:23:35",
                "EndTime": "2016-12-31 16:23:35",
                "IsActive": "1",
                "Sku": "16687",
                "Promote_price": "39.00",
                "goods_remark": "",
                "Area": "",
                "Is_group_goods": "1",
                "goods_id": "16687",
                "goods_img": "goods_images/16687/16687_list_20160310125640.jpg",
                "Size120_180": "goods_images/16687/16687_120_180_20160310125640.jpg",
                "img256_384": "goods_images/16687/16687_256_384_20160310125640.jpg",
                "move_img": "mobiles/mobile_goods_gallery/16687/16687_270_270_20160310125640.jpg",
                "Market_price": "0.00",
                "Shop_price": "108.00",
                "goods_name": "沃多福小麦啤酒500ml听装8听装",
                "Is_book": "0",
                "Sellered": "23640",
                "OriginId": "10016",
                "Cat_name": "德国",
                "SellingPoint": "夏日必选",
                "SupplyMode": "",
                "MobileHighPicture": "mobiles/mobile_goods_gallery/16687/16687_MH.jpg",
                "MobileWidePicture": "mobiles/mobile_goods_gallery/16687/16687_MW.jpg",
                "PreEndTime": "0",
                "Prepaid": "10.00",
                "PreStartTime": "0",
                "OriginCountry": "",
                "AttrSweet": "发酵物 绿色水果 ",
                "AttrTaste": "酸甜如初恋",
                "AttrScore": [
                    {
                        "Attr_value": "",
                        "Score": ""
                    }
                ],
                "AttrDegree": "QBA",
                "ProComment": "圣母之乳是德国弗里茨-温迪诗酒庄出品的一款经典白葡萄酒，具有甘冽甜美的新鲜果香，入口清爽宜人，是非常适合各种场合饮用的德国葡萄酒。",
                "AttrBreed": " %西万尼 %雷司令 %科万尼",
                "gradescore": "95",
                "SaleQty": "7",
                "StockQty": "3852",
                "yxNum": "3852"
            },
            {
                "LinkPicture": "http://image13.wine9.com/activity/2016/04/other/new_01.jpg",
                "Picture": "http://images.wine9.com/activity/2015/index/index825/pj.jpg",
                "Is_HaiTao": "0",
                "TotalQty": "",
                "UsableQty": "0",
                "IsSorting": "",
                "Memo": "",
                "PromId": "2438",
                "PromCode": "1a0ee6a02d0e4def",
                "PromName": "【H5/app】头部导航啤酒",
                "BeginTime": "2015-09-16 16:23:35",
                "EndTime": "2016-12-31 16:23:35",
                "IsActive": "1",
                "Sku": "17525",
                "Promote_price": "39.00",
                "goods_remark": "",
                "Area": "",
                "Is_group_goods": "1",
                "goods_id": "17525",
                "goods_img": "goods_images/17525/17525_list_20160310011201.jpg",
                "Size120_180": "goods_images/17525/17525_120_180_20160310011201.jpg",
                "img256_384": "goods_images/17525/17525_256_384_20160310011201.jpg",
                "move_img": "mobiles/mobile_goods_gallery/17525/17525_270_270_20160310011201.jpg",
                "Market_price": "0.00",
                "Shop_price": "108.00",
                "goods_name": "索伦堡黑啤酒 500ML【8听装】",
                "Is_book": "0",
                "Sellered": "1029",
                "OriginId": "10016",
                "Cat_name": "德国",
                "SellingPoint": "德国原装进口，始终恪守遵循德国质量纯度法案\r\n",
                "SupplyMode": "",
                "MobileHighPicture": "mobiles/mobile_goods_gallery/17525/17525_MH.jpg",
                "MobileWidePicture": "mobiles/mobile_goods_gallery/17525/17525_MW.jpg",
                "PreEndTime": "0",
                "Prepaid": "0.00",
                "PreStartTime": "0",
                "OriginCountry": "",
                "AttrSweet": "",
                "AttrTaste": "",
                "AttrScore": [
                    {
                        "Attr_value": "",
                        "Score": ""
                    }
                ],
                "AttrDegree": "",
                "ProComment": "",
                "AttrBreed": "",
                "gradescore": "95",
                "SaleQty": "3",
                "StockQty": "2601",
                "yxNum": "2601"
            },
            {
                "LinkPicture": "http://image13.wine9.com/activity/2016/04/other/new_01.jpg",
                "Picture": "http://images.wine9.com/activity/2015/index/index825/pj.jpg",
                "Is_HaiTao": "0",
                "TotalQty": "",
                "UsableQty": "0",
                "IsSorting": "",
                "Memo": "",
                "PromId": "2438",
                "PromCode": "1a0ee6a02d0e4def",
                "PromName": "【H5/app】头部导航啤酒",
                "BeginTime": "2015-09-16 16:23:35",
                "EndTime": "2016-12-31 16:23:35",
                "IsActive": "1",
                "Sku": "21199",
                "Promote_price": "39.00",
                "goods_remark": "",
                "Area": "",
                "Is_group_goods": "1",
                "goods_id": "21199",
                "goods_img": "goods_images/21199/21199_list_20160625034427.jpg",
                "Size120_180": "goods_images/21199/21199_120_180_20160625034427.jpg",
                "img256_384": "goods_images/21199/21199_256_384_20160625034427.jpg",
                "move_img": "mobiles/mobile_goods_gallery/21199/21199_270_270_20160625034427.jpg",
                "Market_price": "0.00",
                "Shop_price": "39.00",
                "goods_name": "斯汀伯格小麦啤酒500ML【8听装】",
                "Is_book": "0",
                "Sellered": "0",
                "OriginId": "75",
                "Cat_name": "啤酒",
                "SellingPoint": "德国知名啤酒品牌，啤酒中的液体面包(2016.9.19到期)",
                "SupplyMode": "",
                "MobileHighPicture": "",
                "MobileWidePicture": "",
                "PreEndTime": "0",
                "Prepaid": "0.00",
                "PreStartTime": "0",
                "OriginCountry": "",
                "AttrSweet": "",
                "AttrTaste": "",
                "AttrScore": [
                    {
                        "Attr_value": "",
                        "Score": ""
                    }
                ],
                "AttrDegree": "",
                "ProComment": "",
                "AttrBreed": "",
                "gradescore": "95",
                "SaleQty": "1",
                "StockQty": "32",
                "yxNum": "32"
            },
            {
                "LinkPicture": "http://image13.wine9.com/activity/2016/04/other/new_01.jpg",
                "Picture": "http://images.wine9.com/activity/2015/index/index825/pj.jpg",
                "Is_HaiTao": "0",
                "TotalQty": "",
                "UsableQty": "0",
                "IsSorting": "0",
                "Memo": "",
                "PromId": "2438",
                "PromCode": "1a0ee6a02d0e4def",
                "PromName": "【H5/app】头部导航啤酒",
                "BeginTime": "2015-09-16 16:23:35",
                "EndTime": "2016-12-31 16:23:35",
                "IsActive": "1",
                "Sku": "14554",
                "Promote_price": "39.00",
                "goods_remark": "",
                "Area": "",
                "Is_group_goods": "1",
                "goods_id": "14554",
                "goods_img": "goods_images/11398/11398_list_20140905031315.jpg",
                "Size120_180": "goods_images/11398/11398_120_180_20140905031315.jpg",
                "img256_384": "goods_images/11398/11398_256_384_20140905031315.jpg",
                "move_img": "mobiles/mobile_goods_gallery/11398/11398_270_270_20140905031315.jpg",
                "Market_price": "0.00",
                "Shop_price": "112.00",
                "goods_name": "斯汀伯格黑啤酒 500ml*8听",
                "Is_book": "0",
                "Sellered": "3364",
                "OriginId": "10016",
                "Cat_name": "德国",
                "SellingPoint": "德国知名啤酒品牌，啤酒中的液体面包",
                "SupplyMode": "",
                "MobileHighPicture": "mobiles/mobile_goods_gallery/14554/14554_MH.jpg",
                "MobileWidePicture": "mobiles/mobile_goods_gallery/14554/14554_MW.jpg",
                "PreEndTime": "-201600",
                "Prepaid": "0.00",
                "PreStartTime": "-201600",
                "OriginCountry": "",
                "AttrSweet": "",
                "AttrTaste": "",
                "AttrScore": [
                    {
                        "Attr_value": "",
                        "Score": ""
                    }
                ],
                "AttrDegree": "",
                "ProComment": "",
                "AttrBreed": "",
                "gradescore": "95",
                "SaleQty": "7",
                "StockQty": "1256",
                "yxNum": "1256"
            },
            {
                "LinkPicture": "http://image13.wine9.com/activity/2016/04/other/new_01.jpg",
                "Picture": "http://images.wine9.com/activity/2015/index/index825/pj.jpg",
                "Is_HaiTao": "0",
                "TotalQty": "",
                "UsableQty": "0",
                "IsSorting": "",
                "Memo": "",
                "PromId": "2438",
                "PromCode": "1a0ee6a02d0e4def",
                "PromName": "【H5/app】头部导航啤酒",
                "BeginTime": "2015-09-16 16:23:35",
                "EndTime": "2016-12-31 16:23:35",
                "IsActive": "1",
                "Sku": "21198",
                "Promote_price": "39.00",
                "goods_remark": "",
                "Area": "",
                "Is_group_goods": "1",
                "goods_id": "21198",
                "goods_img": "goods_images/21198/21198_list_20160625033201.jpg",
                "Size120_180": "goods_images/21198/21198_120_180_20160625033201.jpg",
                "img256_384": "goods_images/21198/21198_256_384_20160625033201.jpg",
                "move_img": "mobiles/mobile_goods_gallery/21198/21198_270_270_20160625033201.jpg",
                "Market_price": "0.00",
                "Shop_price": "39.00",
                "goods_name": "猎人黑啤500ML【8听装】",
                "Is_book": "0",
                "Sellered": "0",
                "OriginId": "75",
                "Cat_name": "啤酒",
                "SellingPoint": "口味醇厚，入口清凉口感（保质期至2016.10.1）",
                "SupplyMode": "",
                "MobileHighPicture": "",
                "MobileWidePicture": "",
                "PreEndTime": "0",
                "Prepaid": "0.00",
                "PreStartTime": "0",
                "OriginCountry": "",
                "AttrSweet": "",
                "AttrTaste": "",
                "AttrScore": [
                    {
                        "Attr_value": "",
                        "Score": ""
                    }
                ],
                "AttrDegree": "",
                "ProComment": "",
                "AttrBreed": "",
                "gradescore": "95",
                "SaleQty": "",
                "StockQty": "664",
                "yxNum": "664"
            },
            {
                "LinkPicture": "http://image13.wine9.com/activity/2016/04/other/new_01.jpg",
                "Picture": "http://images.wine9.com/activity/2015/index/index825/pj.jpg",
                "Is_HaiTao": "0",
                "TotalQty": "",
                "UsableQty": "0",
                "IsSorting": "",
                "Memo": "",
                "PromId": "2438",
                "PromCode": "1a0ee6a02d0e4def",
                "PromName": "【H5/app】头部导航啤酒",
                "BeginTime": "2015-09-16 16:23:35",
                "EndTime": "2016-12-31 16:23:35",
                "IsActive": "1",
                "Sku": "21202",
                "Promote_price": "39.00",
                "goods_remark": "",
                "Area": "",
                "Is_group_goods": "1",
                "goods_id": "21202",
                "goods_img": "goods_images/21202/21202_list_20160625040327.jpg",
                "Size120_180": "goods_images/21202/21202_120_180_20160625040327.jpg",
                "img256_384": "goods_images/21202/21202_256_384_20160625040327.jpg",
                "move_img": "mobiles/mobile_goods_gallery/21202/21202_270_270_20160625040327.jpg",
                "Market_price": "0.00",
                "Shop_price": "39.00",
                "goods_name": "奥堡黑啤酒500ml 【8听装】",
                "Is_book": "0",
                "Sellered": "0",
                "OriginId": "75",
                "Cat_name": "啤酒",
                "SellingPoint": "泡沫丰富，口味厚重(2016.11.09)",
                "SupplyMode": "",
                "MobileHighPicture": "",
                "MobileWidePicture": "",
                "PreEndTime": "0",
                "Prepaid": "0.00",
                "PreStartTime": "0",
                "OriginCountry": "",
                "AttrSweet": "",
                "AttrTaste": "",
                "AttrScore": [
                    {
                        "Attr_value": "",
                        "Score": ""
                    }
                ],
                "AttrDegree": "",
                "ProComment": "",
                "AttrBreed": "",
                "gradescore": "95",
                "SaleQty": "1",
                "StockQty": "2092",
                "yxNum": "2092"
            },
            {
                "LinkPicture": "http://image13.wine9.com/activity/2016/04/other/new_01.jpg",
                "Picture": "http://images.wine9.com/activity/2015/index/index825/pj.jpg",
                "Is_HaiTao": "0",
                "TotalQty": "",
                "UsableQty": "0",
                "IsSorting": "",
                "Memo": "",
                "PromId": "2438",
                "PromCode": "1a0ee6a02d0e4def",
                "PromName": "【H5/app】头部导航啤酒",
                "BeginTime": "2015-09-16 16:23:35",
                "EndTime": "2016-12-31 16:23:35",
                "IsActive": "1",
                "Sku": "21197",
                "Promote_price": "39.00",
                "goods_remark": "",
                "Area": "",
                "Is_group_goods": "1",
                "goods_id": "21197",
                "goods_img": "goods_images/21197/21197_list_20160625031850.jpg",
                "Size120_180": "goods_images/21197/21197_120_180_20160625031850.jpg",
                "img256_384": "goods_images/21197/21197_256_384_20160625031850.jpg",
                "move_img": "mobiles/mobile_goods_gallery/21197/21197_270_270_20160625031850.jpg",
                "Market_price": "0.00",
                "Shop_price": "39.00",
                "goods_name": "猎人小麦啤500ML【8听装】",
                "Is_book": "0",
                "Sellered": "4631",
                "OriginId": "75",
                "Cat_name": "啤酒",
                "SellingPoint": "德国进口啤酒，口感纯正（保质期至2016.10.18）",
                "SupplyMode": "",
                "MobileHighPicture": "",
                "MobileWidePicture": "",
                "PreEndTime": "0",
                "Prepaid": "0.00",
                "PreStartTime": "0",
                "OriginCountry": "",
                "AttrSweet": "",
                "AttrTaste": "",
                "AttrScore": [
                    {
                        "Attr_value": "",
                        "Score": ""
                    }
                ],
                "AttrDegree": "",
                "ProComment": "",
                "AttrBreed": "",
                "gradescore": "95",
                "SaleQty": "5",
                "StockQty": "2169",
                "yxNum": "2169"
            },
            {
                "LinkPicture": "http://image13.wine9.com/activity/2016/04/other/new_01.jpg",
                "Picture": "http://images.wine9.com/activity/2015/index/index825/pj.jpg",
                "Is_HaiTao": "0",
                "TotalQty": "",
                "UsableQty": "0",
                "IsSorting": "",
                "Memo": "",
                "PromId": "2438",
                "PromCode": "1a0ee6a02d0e4def",
                "PromName": "【H5/app】头部导航啤酒",
                "BeginTime": "2015-09-16 16:23:35",
                "EndTime": "2016-12-31 16:23:35",
                "IsActive": "1",
                "Sku": "17100",
                "Promote_price": "39.00",
                "goods_remark": "",
                "Area": "",
                "Is_group_goods": "1",
                "goods_id": "17100",
                "goods_img": "goods_images/17100/17100_list_20160310014346.jpg",
                "Size120_180": "goods_images/17100/17100_120_180_20160310014346.jpg",
                "img256_384": "goods_images/17100/17100_256_384_20160310014346.jpg",
                "move_img": "mobiles/mobile_goods_gallery/17100/17100_270_270_20160310014346.jpg",
                "Market_price": "0.00",
                "Shop_price": "108.00",
                "goods_name": "乐森堡小麦啤酒500ml*8听装整箱",
                "Is_book": "0",
                "Sellered": "23937",
                "OriginId": "10016",
                "Cat_name": "德国",
                "SellingPoint": "夏日必选",
                "SupplyMode": "",
                "MobileHighPicture": "mobiles/mobile_goods_gallery/17100/17100_MH.jpg",
                "MobileWidePicture": "mobiles/mobile_goods_gallery/17100/17100_MW.jpg",
                "PreEndTime": "0",
                "Prepaid": "0.00",
                "PreStartTime": "0",
                "OriginCountry": "",
                "AttrSweet": "发酵物 绿色水果 ",
                "AttrTaste": "酸甜如初恋",
                "AttrScore": [
                    {
                        "Attr_value": "",
                        "Score": ""
                    }
                ],
                "AttrDegree": "QBA",
                "ProComment": "圣母之乳是德国弗里茨-温迪诗酒庄出品的一款经典白葡萄酒，具有甘冽甜美的新鲜果香，入口清爽宜人，是非常适合各种场合饮用的德国葡萄酒。",
                "AttrBreed": " %西万尼 %雷司令 %科万尼",
                "gradescore": "95",
                "SaleQty": "8",
                "StockQty": "9985",
                "yxNum": "9985"
            },
            {
                "LinkPicture": "http://image13.wine9.com/activity/2016/04/other/new_01.jpg",
                "Picture": "http://images.wine9.com/activity/2015/index/index825/pj.jpg",
                "Is_HaiTao": "0",
                "TotalQty": "",
                "UsableQty": "0",
                "IsSorting": "",
                "Memo": "",
                "PromId": "2438",
                "PromCode": "1a0ee6a02d0e4def",
                "PromName": "【H5/app】头部导航啤酒",
                "BeginTime": "2015-09-16 16:23:35",
                "EndTime": "2016-12-31 16:23:35",
                "IsActive": "1",
                "Sku": "21192",
                "Promote_price": "99.00",
                "goods_remark": "",
                "Area": "",
                "Is_group_goods": "1",
                "goods_id": "21192",
                "goods_img": "goods_images/21192/21192_list_20160625033034.jpg",
                "Size120_180": "goods_images/21192/21192_120_180_20160625033034.jpg",
                "img256_384": "goods_images/21192/21192_256_384_20160625033034.jpg",
                "move_img": "mobiles/mobile_goods_gallery/21192/21192_270_270_20160625033034.jpg",
                "Market_price": "0.00",
                "Shop_price": "99.00",
                "goods_name": "猎人黑啤500ML【整箱】",
                "Is_book": "0",
                "Sellered": "0",
                "OriginId": "75",
                "Cat_name": "啤酒",
                "SellingPoint": "口味醇厚，入口清凉口感（保质期至2016.10.1）",
                "SupplyMode": "",
                "MobileHighPicture": "",
                "MobileWidePicture": "",
                "PreEndTime": "0",
                "Prepaid": "0.00",
                "PreStartTime": "0",
                "OriginCountry": "",
                "AttrSweet": "",
                "AttrTaste": "",
                "AttrScore": [
                    {
                        "Attr_value": "",
                        "Score": ""
                    }
                ],
                "AttrDegree": "",
                "ProComment": "",
                "AttrBreed": "",
                "gradescore": "95",
                "SaleQty": "2",
                "StockQty": "221",
                "yxNum": "221"
            },
            {
                "LinkPicture": "http://image13.wine9.com/activity/2016/04/other/new_01.jpg",
                "Picture": "http://images.wine9.com/activity/2015/index/index825/pj.jpg",
                "Is_HaiTao": "0",
                "TotalQty": "",
                "UsableQty": "0",
                "IsSorting": "",
                "Memo": "",
                "PromId": "2438",
                "PromCode": "1a0ee6a02d0e4def",
                "PromName": "【H5/app】头部导航啤酒",
                "BeginTime": "2015-09-16 16:23:35",
                "EndTime": "2016-12-31 16:23:35",
                "IsActive": "1",
                "Sku": "21195",
                "Promote_price": "99.00",
                "goods_remark": "",
                "Area": "",
                "Is_group_goods": "1",
                "goods_id": "21195",
                "goods_img": "goods_images/21195/21195_list_20160625035152.jpg",
                "Size120_180": "goods_images/21195/21195_120_180_20160625035152.jpg",
                "img256_384": "goods_images/21195/21195_256_384_20160625035152.jpg",
                "move_img": "mobiles/mobile_goods_gallery/21195/21195_270_270_20160625035152.jpg",
                "Market_price": "0.00",
                "Shop_price": "99.00",
                "goods_name": "奥堡小麦啤酒500ml 【整箱】",
                "Is_book": "0",
                "Sellered": "0",
                "OriginId": "75",
                "Cat_name": "啤酒",
                "SellingPoint": "生态啤酒(2016.10.25到期)",
                "SupplyMode": "",
                "MobileHighPicture": "",
                "MobileWidePicture": "",
                "PreEndTime": "0",
                "Prepaid": "0.00",
                "PreStartTime": "0",
                "OriginCountry": "",
                "AttrSweet": "",
                "AttrTaste": "",
                "AttrScore": "",
                "AttrDegree": "",
                "ProComment": "",
                "AttrBreed": "",
                "gradescore": "95",
                "SaleQty": "7",
                "StockQty": "0",
                "yxNum": "0"
            },
            {
                "LinkPicture": "http://image13.wine9.com/activity/2016/04/other/new_01.jpg",
                "Picture": "http://images.wine9.com/activity/2015/index/index825/pj.jpg",
                "Is_HaiTao": "0",
                "TotalQty": "",
                "UsableQty": "0",
                "IsSorting": "",
                "Memo": "",
                "PromId": "2438",
                "PromCode": "1a0ee6a02d0e4def",
                "PromName": "【H5/app】头部导航啤酒",
                "BeginTime": "2015-09-16 16:23:35",
                "EndTime": "2016-12-31 16:23:35",
                "IsActive": "1",
                "Sku": "21207",
                "Promote_price": "59.00",
                "goods_remark": "",
                "Area": "",
                "Is_group_goods": "1",
                "goods_id": "21207",
                "goods_img": "goods_images/21207/21207_list_20160625035606.jpg",
                "Size120_180": "goods_images/21207/21207_120_180_20160625035606.jpg",
                "img256_384": "goods_images/21207/21207_256_384_20160625035606.jpg",
                "move_img": "mobiles/mobile_goods_gallery/21207/21207_270_270_20160625035606.jpg",
                "Market_price": "0.00",
                "Shop_price": "59.00",
                "goods_name": "奥堡小麦啤酒500ml 【12听装】",
                "Is_book": "0",
                "Sellered": "0",
                "OriginId": "75",
                "Cat_name": "啤酒",
                "SellingPoint": "生态啤酒(2016.10.25到期)",
                "SupplyMode": "",
                "MobileHighPicture": "",
                "MobileWidePicture": "",
                "PreEndTime": "0",
                "Prepaid": "0.00",
                "PreStartTime": "0",
                "OriginCountry": "",
                "AttrSweet": "",
                "AttrTaste": "",
                "AttrScore": "",
                "AttrDegree": "",
                "ProComment": "",
                "AttrBreed": "",
                "gradescore": "95",
                "SaleQty": "1",
                "StockQty": "0",
                "yxNum": "0"
            },
            {
                "LinkPicture": "http://image13.wine9.com/activity/2016/04/other/new_01.jpg",
                "Picture": "http://images.wine9.com/activity/2015/index/index825/pj.jpg",
                "Is_HaiTao": "0",
                "TotalQty": "",
                "UsableQty": "0",
                "IsSorting": "",
                "Memo": "",
                "PromId": "2438",
                "PromCode": "1a0ee6a02d0e4def",
                "PromName": "【H5/app】头部导航啤酒",
                "BeginTime": "2015-09-16 16:23:35",
                "EndTime": "2016-12-31 16:23:35",
                "IsActive": "1",
                "Sku": "21201",
                "Promote_price": "39.00",
                "goods_remark": "",
                "Area": "",
                "Is_group_goods": "1",
                "goods_id": "21201",
                "goods_img": "goods_images/21201/21201_list_20160625035402.jpg",
                "Size120_180": "goods_images/21201/21201_120_180_20160625035402.jpg",
                "img256_384": "goods_images/21201/21201_256_384_20160625035402.jpg",
                "move_img": "mobiles/mobile_goods_gallery/21201/21201_270_270_20160625035402.jpg",
                "Market_price": "0.00",
                "Shop_price": "39.00",
                "goods_name": "奥堡小麦啤酒500ml 【8听装】",
                "Is_book": "0",
                "Sellered": "0",
                "OriginId": "75",
                "Cat_name": "啤酒",
                "SellingPoint": "生态啤酒（2016.10.25到期）",
                "SupplyMode": "",
                "MobileHighPicture": "",
                "MobileWidePicture": "",
                "PreEndTime": "0",
                "Prepaid": "0.00",
                "PreStartTime": "0",
                "OriginCountry": "",
                "AttrSweet": "",
                "AttrTaste": "",
                "AttrScore": [
                    {
                        "Attr_value": "",
                        "Score": ""
                    }
                ],
                "AttrDegree": "",
                "ProComment": "",
                "AttrBreed": "",
                "gradescore": "95",
                "SaleQty": "",
                "StockQty": "0",
                "yxNum": "0"
            }
        ]
    }
}